quick_spice_manager/__init__.py
quick_spice_manager/dirs.py
quick_spice_manager/py.typed
quick_spice_manager/spice_manager.py
quick_spice_manager/utils.py
quick_spice_manager-0.0.3.dist-info/METADATA
quick_spice_manager-0.0.3.dist-info/WHEEL
quick_spice_manager-0.0.3.dist-info/licenses/LICENSE
quick_spice_manager-0.0.3.dist-info/RECORD
