Metadata-Version: 2.4
Name: quick-spice-manager
Version: 0.0.3
Project-URL: documentation, https://luca-penasa.github.io/quick-spice-manager
Project-URL: homepage, https://luca-penasa.github.io/quick-spice-manager
Project-URL: repository, https://github.com/luca-penasa/quick-spice-manager
Author-email: Luca Penasa <luca.penasa@gmail.com>
License-Expression: MIT
License-File: LICENSE
Classifier: Development Status :: 4 - Beta
Classifier: Intended Audience :: Developers
Classifier: Operating System :: OS Independent
Classifier: Programming Language :: Python
Classifier: Programming Language :: Python :: 3
Classifier: Programming Language :: Python :: 3.10
Classifier: Programming Language :: Python :: 3.11
Classifier: Programming Language :: Python :: 3.12
Classifier: Programming Language :: Python :: 3.13
Classifier: Topic :: Software Development :: Libraries :: Python Modules
Classifier: Typing :: Typed
Requires-Python: <4.0,>=3.10
Requires-Dist: attrs>=24.2.0
Requires-Dist: importlib-metadata>=8.5.0
Requires-Dist: loguru>=0.7.2
Requires-Dist: pandas>=2.2.3
Requires-Dist: planetary-coverage>=1.1.1
Requires-Dist: platformdirs>=4.3.6
